{"xq+h08BshcMa/fwuA8yNAQ==":"imageedit_4-8896372564-96x28.png","MCJ9LcFdzcKTJ5rOsUJItA==":"output-onlinepngtools%20(2)-300x300.png","x+6CMJmfna9ChTrO9DrzPQ==":"maestro-logo-96x75.png","9GeCp1Z8xWQk5biP38O5Xg==":"output-onlinepngtools%20(2)-122x122.png","rbzFA6vPKLS8BcObYzgnbg==":"gta-5-pc-370x172.jpg","SGazzi3ApalPbKRf9cNR9w==":"minecraft-wallpaper-370x231.jpg","R7iLfxFGwEu+N/in1WGwIw==":"minecraft-wallpaper-1-370x231.jpg","chAAABrvgm8nZqwMcc5jBg==":"minecraft-wallpaper-2-370x231.jpg","+U0RaZ16jNFd3R/PeKNH/Q==":"geforcenow_blog-370x206.jpg","g5HQCKu38B0EwhsGpL9ccQ==":"bgmain-370x261.jpg","9aI8JoDqdRuD7F+wC0GRnw==":"bgmain-1-370x261.jpg","YfG4qNLmx1A7cmgfXam2tA==":"85af6c_73b77e0e445d410690ae1e402fe39b75_mv2.webp","pf4WjmpHATK57rnyd6pbrw==":"output-onlinepngtools%20(1)-122x122.png","Ox1CsNDBKBfRPAEF1H3Yrw==":"output-onlinepngtools%20(2)-192x192.png","/381FAL7LgpExOTc5AsPdw==":"fortnite-playground-lg.webp","oCqoz0VbFE3TlLm3kgUFGg==":"index-hero-og-1200x630.jpg","L+26uQ2W+czvfphdgAZXGg==":"imageedit_4-8896372564-180x52.png"}